pyramid_sanity/__init__.py
pyramid_sanity/exceptions.py
pyramid_sanity/tweens.py
pyramid_sanity-1.0.4.dist-info/LICENSE
pyramid_sanity-1.0.4.dist-info/METADATA
pyramid_sanity-1.0.4.dist-info/WHEEL
pyramid_sanity-1.0.4.dist-info/top_level.txt
pyramid_sanity-1.0.4.dist-info/RECORD
