Metadata-Version: 2.1
Name: pyramid-sanity
Version: 1.0.4
Summary: Sensible defaults to catch bad behavior.
Home-page: https://github.com/hypothesis/pyramid-sanity
Project-URL: Bug Tracker, https://github.com/hypothesis/pyramid-sanity/issues
Project-URL: Changelog, https://github.com/hypothesis/pyramid-sanity/releases
Classifier: Programming Language :: Python :: 3
Classifier: License :: OSI Approved :: BSD License
Classifier: Intended Audience :: Developers
Requires-Python: >=3.8
License-File: LICENSE
Requires-Dist: pyramid
